errcron/__init__.py
errcron/action.py
errcron/bot.py
errcron/cronjob.py
errcron-0.4.4.dist-info/DESCRIPTION.rst
errcron-0.4.4.dist-info/METADATA
errcron-0.4.4.dist-info/RECORD
errcron-0.4.4.dist-info/WHEEL
errcron-0.4.4.dist-info/entry_points.txt
errcron-0.4.4.dist-info/metadata.json
errcron-0.4.4.dist-info/top_level.txt
