Metadata-Version: 2.0
Name: errcron
Version: 0.4.4
Summary: Crontab implementation for Errbot
Home-page: https://github.com/attakei/errcron
Author: attakei
Author-email: attakei@users.noreply.github.com
License: GPLv3
Keywords: errbot plugin crontab
Platform: UNKNOWN
Classifier: Development Status :: 3 - Alpha
Classifier: License :: OSI Approved :: GNU General Public License v3 (GPLv3)
Classifier: Programming Language :: Python :: 2.7
Classifier: Programming Language :: Python :: 3.4
Classifier: Programming Language :: Python :: 3.5
Classifier: Programming Language :: Python :: 3.6
Classifier: Topic :: Communications :: Chat
Requires-Dist: six
Requires-Dist: crontab
Requires-Dist: pytz
Provides-Extra: test
Requires-Dist: pytest-pep8; extra == 'test'
Requires-Dist: pytest-flakes; extra == 'test'
Requires-Dist: pytest-cov; extra == 'test'
Requires-Dist: pytest; extra == 'test'
Requires-Dist: freezegun; extra == 'test'
Requires-Dist: codeclimate-test-reporter; extra == 'test'
Requires-Dist: coverage (<4.4,>=4.0); extra == 'test'
